adafdr/__init__.py
adafdr/data_loader.py
adafdr/method.py
adafdr/sideinfo_release.py
adafdr/util.py
adafdr/data/Adipose_Subcutaneous_chr21_300k
adafdr/data/Adipose_Visceral_Omentum_chr21_300k
adafdr/data/GTEx_small.pickle
adafdr/data/airway
adafdr/data/bottomly
adafdr/data/pasilla
adafdr-0.1.8.dist-info/LICENSE
adafdr-0.1.8.dist-info/METADATA
adafdr-0.1.8.dist-info/WHEEL
adafdr-0.1.8.dist-info/top_level.txt
adafdr-0.1.8.dist-info/RECORD
