Metadata-Version: 2.1
Name: adafdr
Version: 0.1.8
Summary: A fast and covariate-adaptive method for multiple hypothesis testing
Home-page: https://github.com/martinjzhang/adafdr
Author: Martin Zhang, Fei Xia, James Zou
Author-email: jinye@stanford.edu
License: UNKNOWN
Platform: UNKNOWN
Classifier: Programming Language :: Python :: 3
Classifier: License :: OSI Approved :: MIT License
Classifier: Operating System :: OS Independent
Requires-Dist: numpy
Requires-Dist: scipy
Requires-Dist: scikit-learn
Requires-Dist: torch (==1.4.0)
Requires-Dist: matplotlib
